.editorconfig
.pylintrc
CHANGES.md
LICENSE
MANIFEST.in
Makefile
README.md
increment_version.sh
pyproject.toml
requirements.txt
run-tests.sh
setup.cfg
setup.py
invenio_config_kth/__init__.py
invenio_config_kth/config.py
invenio_config_kth/ext.py
invenio_config_kth/startup.py
invenio_config_kth/utils.py
invenio_config_kth.egg-info/PKG-INFO
invenio_config_kth.egg-info/SOURCES.txt
invenio_config_kth.egg-info/dependency_links.txt
invenio_config_kth.egg-info/entry_points.txt
invenio_config_kth.egg-info/not-zip-safe
invenio_config_kth.egg-info/requires.txt
invenio_config_kth.egg-info/top_level.txt
invenio_config_kth/permissions/__init__.py
invenio_config_kth/permissions/generators.py
invenio_config_kth/permissions/policies.py
tests/__init__.py
tests/test_invenio_config_kth.py