Metadata-Version: 2.1
Name: invenio-config-kth
Version: 1.2.8
Summary: invenio-config-kth
Home-page: https://github.com/Samk13/invenio-config-kth
Author: KTH Royal Institute of Technology
Author-email: info@kth.se
License: MIT
Keywords: invenio rdm config kth
Platform: any
Classifier: Environment :: Web Environment
Classifier: Intended Audience :: Developers
Classifier: License :: OSI Approved :: MIT License
Classifier: Operating System :: OS Independent
Classifier: Programming Language :: Python
Classifier: Topic :: Internet :: WWW/HTTP :: Dynamic Content
Classifier: Topic :: Software Development :: Libraries :: Python Modules
Classifier: Programming Language :: Python :: 3
Classifier: Programming Language :: Python :: 3.7
Classifier: Programming Language :: Python :: 3.8
Classifier: Programming Language :: Python :: 3.9
Classifier: Programming Language :: Python :: 3.10
Requires-Python: >=3.7
Provides-Extra: tests
License-File: LICENSE
